myomappy-0.1.1.dist-info/METADATA
myomappy-0.1.1.dist-info/WHEEL
myomappy-0.1.1.dist-info/LICENSE.txt
myomappy/rungekutta/_runge_kutta_4_calcs.cpython-311-darwin.so
myomappy/__init__.py
myomappy/rungekutta/__init__.py
myomappy/rungekutta/runge_kutta_4.py
myomappy-0.1.1.dist-info/RECORD
