Metadata-Version: 2.1
Name: myomappy
Version: 0.1.1
Summary: A Python package for diffusion tensor-based tractography in the heart.
Author-Email: Spencer Bertram <spenbert02@gmail.com>
License:                     GNU AFFERO GENERAL PUBLIC LICENSE
Project-URL: Homepage, https://github.com/Spenbert02/myomappy
Project-URL: Issues, https://github.com/Spenbert02/myomappy/issues
Requires-Python: >=3.11
